veralux/__init__.py
veralux-0.0.0.dist-info/LICENSE
veralux-0.0.0.dist-info/METADATA
veralux-0.0.0.dist-info/WHEEL
veralux-0.0.0.dist-info/top_level.txt
veralux-0.0.0.dist-info/RECORD
