Metadata-Version: 2.2
Name: veralux
Version: 0.0.0
Summary: Effortlessly build, extend, and deploy sophisticated language-model-based agents
Author: Brent Carpenetti
Author-email: Brent Carpenetti <brentcarpenetti@gmail.com>
License: MIT License
License-File: LICENSE
Dynamic: author
